isomedia
