Metadata-Version: 1.0
Name: isomedia
Version: 0.2.3
Summary: This is another ISO base media format file parser.
Home-page: https://github.com/flxf/isomedia
Author: Felix Fung
Author-email: felix.the.cheshire.cat@gmail.com
License: UNKNOWN
Keywords: mp4,isom
Platform: UNKNOWN
